{
    "WINDOWS": {
        "platform": "windows",
        "path": "windows",
        "configuration": {
            "ignoreRuleHints": false
        },
        "defines": {
            "adguard": true,
            "adguard_app_windows": true
        }
    },
    "MAC": {
        "platform": "mac",
        "path": "mac",
        "configuration": {
            "ignoreRuleHints": false
        },
        "defines": {
            "adguard": true,
            "adguard_app_mac": true
        }
    },
    "MAC_V2": {
        "platform": "mac",
        "path": "mac_v2",
        "configuration": {
            "ignoreRuleHints": false
        },
        "defines": {
            "adguard": true,
            "adguard_app_mac": true
        }
    },
    "ANDROID": {
        "platform": "android",
        "path": "android",
        "configuration": {
            "ignoreRuleHints": false
        },
        "defines": {
            "adguard": true,
            "adguard_app_android": true
        }
    },
    "EXTENSION_CHROMIUM": {
        "platform": "ext_chromium",
        "path": "extension/chromium",
        "configuration": {
            "removeRulePatterns": [
                "^((?!#%#).)*\\$\\$|\\$\\@\\$",
                "\\$(.*,)?replace=",
                "important,replace=",
                "\\$(.*,)?app",
                "\\$network",
                "\\$protobuf",
                "important,protobuf",
                "\\$extension",
                ",extension",
                "\\$hls=",
                ",hls=",
                "\\$jsonprune=",
                ",jsonprune=",
                "\\$content",
                ",content"
            ],
            "ignoreRuleHints": false
        },
        "defines": {
            "adguard": true,
            "adguard_ext_chromium": true
        }
    },
    "EXTENSION_EDGE": {
        "platform": "ext_edge",
        "path": "extension/edge",
        "configuration": {
            "removeRulePatterns": [
                "^((?!#%#).)*\\$\\$|\\$\\@\\$",
                "\\$(.*,)?replace=",
                "important,replace=",
                "\\$(.*,)?app",
                "\\$network",
                "\\$protobuf",
                "important,protobuf",
                "\\$extension",
                ",extension",
                "\\$hls=",
                ",hls=",
                "\\$jsonprune=",
                ",jsonprune=",
                "\\$content",
                ",content"
            ],
            "ignoreRuleHints": false
        },
        "defines": {
            "adguard": true,
            "adguard_ext_edge": true,
            "adguard_ext_chromium": true
        }
    },
    "EXTENSION_OPERA": {
        "platform": "ext_opera",
        "path": "extension/opera",
        "configuration": {
            "removeRulePatterns": [
                "^((?!#%#).)*\\$\\$|\\$\\@\\$",
                "\\$(.*,)?replace=",
                "important,replace=",
                "\\$(.*,)?app",
                "\\$network",
                "\\$protobuf",
                "important,protobuf",
                "\\$extension",
                ",extension",
                "\\$hls=",
                ",hls=",
                "\\$jsonprune=",
                ",jsonprune=",
                "\\$content",
                ",content"
            ],
            "ignoreRuleHints": false
        },
        "defines": {
            "adguard": true,
            "adguard_ext_opera": true,
            "adguard_ext_chromium": true
        }
    },
    "EXTENSION_FIREFOX": {
        "platform": "ext_ff",
        "path": "extension/firefox",
        "configuration": {
            "removeRulePatterns": [
                "^((?!#%#).)*\\$\\$|\\$\\@\\$",
                "\\$(.*,)?app",
                "\\$network",
                "\\$protobuf",
                "important,protobuf",
                "\\$extension",
                ",extension"
            ],
            "ignoreRuleHints": false
        },
        "defines": {
            "adguard": true,
            "adguard_ext_firefox": true
        }
    },
    "EXTENSION_SAFARI": {
        "platform": "ext_safari",
        "path": "extension/safari",
        "configuration": {
            "removeRulePatterns": [
                "\\$domain=\/",
                ",domain=\/",
                "^((?!#%#).)*\\$\\$|\\$\\@\\$",
                "\\$extension",
                ",extension",
                "\\$removeparam",
                ",removeparam",
                "\\$removeheader",
                ",removeheader",
                "\\$(.*,)?mp4",
                "\\$(.*,)?replace=",
                "\\$stealth",
                ",stealth",
                "\\$cookie",
                ",cookie",
                "important,replace=",
                "\\$(.*,)?app",
                "\\$protobuf",
                "important,protobuf",
                "\\$redirect=",
                ",redirect=",
                "\\$redirect-rule=",
                ",redirect-rule=",
                "\\$empty",
                ",empty",
                "\\$webrtc",
                "\\$csp",
                "\\$network",
                "\\$hls=",
                ",hls=",
                "\\$jsonprune=",
                ",jsonprune="
            ],
            "ignoreRuleHints": false
        },
        "defines": {
            "adguard": true,
            "adguard_ext_safari": true
        }
    },
    "IOS": {
        "platform": "ios",
        "path": "ios",
        "configuration": {
            "removeRulePatterns": [
                "\\$domain=\/",
                ",domain=\/",
                "^((?!#%#).)*\\$\\$|\\$\\@\\$",
                "\\$extension",
                ",extension",
                "\\$removeparam",
                ",removeparam",
                "\\$removeheader",
                ",removeheader",
                "\\$(.*,)?mp4",
                "\\$(.*,)?replace=",
                "\\$stealth",
                ",stealth",
                "\\$cookie",
                ",cookie",
                "important,replace=",
                "\\$(.*,)?app",
                "\\$protobuf",
                "important,protobuf",
                "\\$redirect=",
                ",redirect=",
                "\\$redirect-rule=",
                ",redirect-rule=",
                "\\$empty",
                ",empty",
                "\\$webrtc",
                "\\$csp",
                "\\$network",
                "\\$hls=",
                ",hls=",
                "\\$jsonprune=",
                ",jsonprune="
            ],
            "ignoreRuleHints": false
        },
        "defines": {
            "adguard": true,
            "adguard_app_ios": true
        }
    },
    "EXTENSION_ANDROID_CONTENT_BLOCKER": {
        "platform": "ext_android_cb",
        "path": "extension/android-content-blocker",
        "configuration": {
            "removeRulePatterns": [
                "\\$domain=\/",
                ",domain=\/",
                "^((?!#%#).)*\\$\\$|\\$\\@\\$",
                "\\$extension",
                ",extension",
                "\\$removeparam",
                ",removeparam",
                "\\$removeheader",
                ",removeheader",
                "#%#",
                "#@%#",
                "#\\$#",
                "#@\\$#",
                "\\$(.*,)?mp4",
                "\\$(.*,)?replace=",
                "\\$stealth",
                ",stealth",
                "\\$cookie",
                ",cookie",
                "\\$empty",
                "important,replace=",
                "\\$(.*,)?app",
                "\\$protobuf",
                "important,protobuf",
                "\\[-ext-",
                "\\$csp",
                ":has\\(",
                ":has-text\\(",
                ":contains\\(",
                ":matches-css\\(",
                ":matches-attr\\(",
                ":matches-property\\(",
                ":xpath\\(",
                ":nth-ancestor\\(",
                ":upward\\(",
                ":remove\\(",
                ":matches-css-before\\(",
                ":matches-css-after\\(",
                ":-abp-has\\(",
                ":-abp-contains\\(",
                "#\\?#",
                "#\\$\\?#",
                "#@\\?#",
                "#@\\$\\?#",
                "\\$redirect=",
                ",redirect=",
                "\\$redirect-rule=",
                ",redirect-rule=",
                "\\$hls=",
                ",hls=",
                "\\$jsonprune=",
                ",jsonprune="
            ],
            "ignoreRuleHints": false
        },
        "defines": {
            "adguard": true,
            "adguard_ext_android_cb": true
        }
    },
    "EXTENSION_UBLOCK": {
        "platform": "ext_ublock",
        "path": "extension/ublock",
        "configuration": {
            "removeRulePatterns": [
                "^((?!#%#).)*\\$\\$|\\$\\@\\$",
                "\\$(.*,)?mp4",
                "\\$(.*,)?replace=",
                "\\$stealth",
                ",stealth",
                "\\$cookie",
                ",cookie",
                "important,replace=",
                "\\$(.*,)?app",
                "\\$network",
                "\\$protobuf",
                "important,protobuf",
                "\\$extension",
                ",extension",
                "\\$jsinject",
                ",jsinject",
                "\\$urlblock",
                ",urlblock",
                "\\$content",
                ",content(,|$)",
                "$webrtc",
                "#\\$#@media ",
                "\\$hls=",
                ",hls=",
                "\\$jsonprune=",
                ",jsonprune="
            ],
            "ignoreRuleHints": false,
            "adbHeader": "![Adblock Plus 2.0]"
        },
        "defines": {
            "ext_ublock": true
        }
    }
}
